setup.py
laredoyin_probability/Binomialdistribution.py
laredoyin_probability/Gaussiandistribution.py
laredoyin_probability/Generaldistribution.py
laredoyin_probability/__init__.py
laredoyinprobability.egg-info/PKG-INFO
laredoyinprobability.egg-info/SOURCES.txt
laredoyinprobability.egg-info/dependency_links.txt
laredoyinprobability.egg-info/not-zip-safe
laredoyinprobability.egg-info/top_level.txt