Metadata-Version: 1.0
Name: laredoyinprobability
Version: 0.1.6
Summary: Gaussian and Binomial distributions
Home-page: UNKNOWN
Author: Damilare Adedoyin
Author-email: damilare182@gmail.com
License: UNKNOWN
Platform: UNKNOWN
